{
	"schemaVersion": 1,
	"id": "easyrecycling",
	"version": "${version}",
	"name": "EasyRecycling",
	"description": "This is an example description! Tell everyone what your mod is about!",
	"authors": [
		"GordyJack"
	],
	"contact": {
		"homepage": "https://fabricmc.net/",
		"sources": "https://github.com/FabricMC/fabric-example-mod"
	},
	"license": "LGPLv3",
	"icon": "assets/easyrecycling/icon.png",
	"environment": "*",
	"entrypoints": {
		"main": [
			"net.gordyjack.easyrecycling.EasyRecycling"
		],
		"client": [
			"net.gordyjack.easyrecycling.EasyRecyclingClient"
		],
		"fabric-datagen": [
			"net.gordyjack.easyrecycling.EasyRecyclingDataGenerator"
		]
	},
	"depends": {
		"fabricloader": ">=0.14.19",
		"minecraft": "1.20-beta.1",
		"java": ">=17",
		"fabric-api": "*"
	},
	"suggests": {
		"another-mod": "*"
	}
}